nano_vllm_npu-0.0.1.post1.dist-info/licenses/LICENSE
nanovllmnpu/__init__.py
nanovllmnpu/config.py
nanovllmnpu/llm.py
nanovllmnpu/sampling_params.py
nanovllmnpu/engine/block_manager.py
nanovllmnpu/engine/llm_engine.py
nanovllmnpu/engine/model_runner.py
nanovllmnpu/engine/scheduler.py
nanovllmnpu/engine/sequence.py
nanovllmnpu/layers/activation.py
nanovllmnpu/layers/attention.py
nanovllmnpu/layers/embed_head.py
nanovllmnpu/layers/layernorm.py
nanovllmnpu/layers/linear.py
nanovllmnpu/layers/rotary_embedding.py
nanovllmnpu/layers/sampler.py
nanovllmnpu/models/qwen3.py
nanovllmnpu/utils/context.py
nanovllmnpu/utils/loader.py
nano_vllm_npu-0.0.1.post1.dist-info/METADATA
nano_vllm_npu-0.0.1.post1.dist-info/WHEEL
nano_vllm_npu-0.0.1.post1.dist-info/top_level.txt
nano_vllm_npu-0.0.1.post1.dist-info/RECORD
