Metadata-Version: 2.4
Name: nano-vllm-npu
Version: 0.0.1.post1
Summary: a lightweight vLLM implementation built from scratch and runs on NPU.
Author: VoidVelocity
License: MIT License
Project-URL: Homepage, https://github.com/voidvelocity/nano-vllm-npu
Requires-Python: <3.13,>=3.10
License-File: LICENSE
Requires-Dist: torch>=2.4.0
Requires-Dist: torch-npu>=2.4.0
Requires-Dist: transformers>=4.51.0
Requires-Dist: xxhash
Dynamic: license-file
